{"question": "Can I be unemployed while approved for OPT, and still legally remain in the U.S.?", "answer": "\nThe new regulations published on April 8th, 2008, limit periods of unemployment during post-completion OPT. F-1 status is now dependent upon employment, within the following parameters:\nStudents may not accrue an aggregate of more than 90 days of unemployment during any post-completion OPT carried out under the initial 12-month post-completion OPT authorization.\nStudents granted a 17-month OPT extension may not accrue an aggregate of more than 120 days of unemployment.\n\n", "sentence_tokenizer": ["Can I be unemployed while approved for OPT, and still legally remain in the U.S.?", "The new regulations published on April 8th, 2008, limit periods of unemployment during post-completion OPT.", "F-1 status is now dependent upon employment, within the following parameters:\nStudents may not accrue an aggregate of more than 90 days of unemployment during any post-completion OPT carried out under the initial 12-month post-completion OPT authorization.", "Students granted a 17-month OPT extension may not accrue an aggregate of more than 120 days of unemployment."], "words_tokenizer": ["Can", "I", "be", "unemployed", "while", "approved", "for", "OPT", ",", "and", "still", "legally", "remain", "in", "the", "U.S.", "?", "The", "new", "regulations", "published", "on", "April", "8th", ",", "2008", ",", "limit", "periods", "of", "unemployment", "during", "post-completion", "OPT", ".", "F-1", "status", "is", "now", "dependent", "upon", "employment", ",", "within", "the", "following", "parameters", ":", "Students", "may", "not", "accrue", "an", "aggregate", "of", "more", "than", "90", "days", "of", "unemployment", "during", "any", "post-completion", "OPT", "carried", "out", "under", "the", "initial", "12-month", "post-completion", "OPT", "authorization", ".", "Students", "granted", "a", "17-month", "OPT", "extension", "may", "not", "accrue", "an", "aggregate", "of", "more", "than", "120", "days", "of", "unemployment", "."], "words_without_stop_words": ["Can", "I", "unemployed", "approved", "OPT", ",", "still", "legally", "remain", "U.S.", "?", "The", "new", "regulations", "published", "April", "8th", ",", "2008", ",", "limit", "periods", "unemployment", "post-completion", "OPT", ".", "F-1", "status", "dependent", "upon", "employment", ",", "within", "following", "parameters", ":", "Students", "may", "accrue", "aggregate", "90", "days", "unemployment", "post-completion", "OPT", "carried", "initial", "12-month", "post-completion", "OPT", "authorization", ".", "Students", "granted", "17-month", "OPT", "extension", "may", "accrue", "aggregate", "120", "days", "unemployment", "."], "words_with_stemming": ["can", "i", "unemploy", "approv", "opt", ",", "still", "legal", "remain", "u.s.", "?", "the", "new", "regul", "publish", "april", "8th", ",", "2008", ",", "limit", "period", "unemploy", "post-complet", "opt", ".", "f-1", "status", "depend", "upon", "employ", ",", "within", "follow", "paramet", ":", "student", "may", "accru", "aggreg", "90", "day", "unemploy", "post-complet", "opt", "carri", "initi", "12-month", "post-complet", "opt", "author", ".", "student", "grant", "17-month", "opt", "extens", "may", "accru", "aggreg", "120", "day", "unemploy", "."], "words_with_lemmatization": ["Can", "I", "unemployed", "approve", "OPT", ",", "still", "legally", "remain", "U.S.", "?", "The", "new", "regulation", "publish", "April", "8th", ",", "2008", ",", "limit", "period", "unemployment", "post-completion", "OPT", ".", "F-1", "status", "dependent", "upon", "employment", ",", "within", "follow", "parameter", ":", "Students", "may", "accrue", "aggregate", "90", "day", "unemployment", "post-completion", "OPT", "carry", "initial", "12-month", "post-completion", "OPT", "authorization", ".", "Students", "grant", "17-month", "OPT", "extension", "may", "accrue", "aggregate", "120", "day", "unemployment", "."], "words_with_pos_tags": [["Can", "MD"], ["I", "PRP"], ["unemployed", "JJ"], ["approved", "VBD"], ["OPT", "NNP"], [",", ","], ["still", "RB"], ["legally", "RB"], ["remain", "VBP"], ["U.S.", "NNP"], ["?", "."], ["The", "DT"], ["new", "JJ"], ["regulations", "NNS"], ["published", "VBN"], ["April", "NNP"], ["8th", "CD"], [",", ","], ["2008", "CD"], [",", ","], ["limit", "NN"], ["periods", "NNS"], ["unemployment", "NN"], ["post-completion", "NN"], ["OPT", "NNP"], [".", "."], ["F-1", "NNP"], ["status", "NN"], ["dependent", "NN"], ["upon", "IN"], ["employment", "NN"], [",", ","], ["within", "IN"], ["following", "VBG"], ["parameters", "NNS"], [":", ":"], ["Students", "NNS"], ["may", "MD"], ["accrue", "VB"], ["aggregate", "VB"], ["90", "CD"], ["days", "NNS"], ["unemployment", "NN"], ["post-completion", "NN"], ["OPT", "NNP"], ["carried", "VBD"], ["initial", "JJ"], ["12-month", "JJ"], ["post-completion", "NN"], ["OPT", "NNP"], ["authorization", "NN"], [".", "."], ["Students", "NNS"], ["granted", "VBD"], ["17-month", "JJ"], ["OPT", "NNP"], ["extension", "NN"], ["may", "MD"], ["accrue", "VB"], ["aggregate", "VB"], ["120", "CD"], ["days", "NNS"], ["unemployment", "NN"], [".", "."]], "parse_tree_string": "(ROOT\n  (SQ (MD Can)\n    (NP (PRP I))\n    (VP\n      (VP (VB be)\n        (ADJP (JJ unemployed))\n        (SBAR (IN while)\n          (S\n            (VP (VBN approved)\n              (PP (IN for)\n                (NP (NNP OPT)))))))\n      (, ,)\n      (CC and)\n      (ADVP (RB still))\n      (VP\n        (ADVP (RB legally))\n        (VB remain)\n        (PP (IN in)\n          (NP (DT the) (NNP U.S.)))))\n    (. ?)))(ROOT\n  (S\n    (NP\n      (NP (DT The) (JJ new) (NNS regulations))\n      (VP (VBN published)\n        (PP (IN on)\n          (NP (NNP April) (JJ 8th))))\n      (, ,)\n      (NP (CD 2008))\n      (, ,))\n    (VP (NN limit)\n      (NP\n        (NP (NNS periods))\n        (PP (IN of)\n          (NP (NN unemployment))))\n      (PP (IN during)\n        (NP (JJ post-completion) (NN OPT))))\n    (. .)))(ROOT\n  (S\n    (S\n      (NP (NN F-1) (NN status))\n      (VP (VBZ is)\n        (ADVP (RB now))\n        (ADJP (JJ dependent)\n          (PP (IN upon)\n            (NP (NN employment))))\n        (, ,)\n        (PP (IN within)\n          (NP (DT the) (VBG following) (NNS parameters)))))\n    (: :)\n    (S\n      (NP (NNS Students))\n      (VP (MD may) (RB not)\n        (VP (VB accrue)\n          (NP\n            (NP (DT an) (NN aggregate))\n            (PP (IN of)\n              (NP\n                (NP\n                  (QP (JJR more) (IN than) (CD 90))\n                  (NNS days))\n                (PP (IN of)\n                  (NP (NN unemployment))))))\n          (PP (IN during)\n            (NP\n              (NP (DT any) (JJ post-completion) (NN OPT))\n              (VP (VBD carried)\n                (PRT (RP out))\n                (PP (IN under)\n                  (NP (DT the) (JJ initial) (JJ 12-month) (JJ post-completion) (NN OPT) (NN authorization)))))))))\n    (. .)))(ROOT\n  (S\n    (NP (NNS Students))\n    (VP (VBD granted)\n      (SBAR\n        (S\n          (NP (DT a) (JJ 17-month) (NNP OPT) (NN extension))\n          (VP (MD may) (RB not)\n            (VP (VB accrue)\n              (NP\n                (NP (DT an) (NN aggregate))\n                (PP (IN of)\n                  (NP\n                    (NP\n                      (QP (JJR more) (IN than) (CD 120))\n                      (NNS days))\n                    (PP (IN of)\n                      (NP (NN unemployment)))))))))))\n    (. .)))", "hypernyms_list": ["sustain", "life", "extremity", "intellectual", "play", "time_period", "delay", "rule", "bring", "calendar_day", "action", "persevere", "value", "promote", "stretching", "opportunity", "agree", "quantity", "originate", "compensate", "extent", "boundary", "occupation", "travel", "practice", "hold", "dissemination", "legal_document", "check", "telephone", "have", "result", "sum", "meaning", "part", "whole", "transfer", "address", "understand", "include", "era", "dominance", "permission", "give_birth", "enrollee", "imitate", "range", "gregorian_calendar_month", "act", "produce", "concept", "organic_process", "evaluate", "effect", "hit", "move", "continue", "follow", "create_verbally", "nourish", "state", "activity", "be", "property", "work_time", "authorize", "win", "circulate", "end", "recipient", "education", "sidereal_time", "dance", "constant", "obtain", "publicize", "choose", "time_unit", "time_interval", "expansion", "punctuation", "string", "propel", "communicate", "imply", "fundamental_quantity", "discharge", "material", "addition", "geological_time", "influence", "longness", "federal_government", "give", "grow", "perform", "management", "analyze", "drink", "factor", "indefinite_quantity", "control", "obey", "appropriate", "time", "bear"], "hyponyms_list": ["saturation", "lactation", "peacetime", "caste", "accede", "edit", "nobility", "retirement", "despair", "wartime", "sovereignty", "spread", "shadow", "real_time", "eve", "utmost", "preservation", "day", "iniquity", "recycling", "supplant", "discomfort", "duration", "stalk", "assize", "alumnus", "school_day", "maximum", "rainy_day", "slot", "chase", "polling_day", "vouchsafe", "allowance", "way", "stretch", "enclose", "indexation", "heel", "wetness", "dominance", "saint's_day", "social_station", "standing", "groundhog_day", "pan_american_day", "semester", "lunar_day", "improvement", "tomorrow", "medical_student", "long_run", "cart", "prepossession", "school", "seminarian", "catechumen", "quarter-century", "assert", "ministry", "piecework", "term", "leap_day", "market_day", "regulation_time", "license", "half-century", "cinco_de_mayo", "november_5", "pose", "scholar", "hours", "midsummer_eve", "study_hall", "mutism", "walk_around", "past", "philosopher", "ionization", "half_life", "rank", "lubrication", "inauguration_day", "verge", "morrow", "dignity", "anchorage", "speed_limit", "curvature", "game_law", "overtime", "prehistory", "silence", "sleep", "tilth", "exoneration", "working_principle", "collegian", "psychological_state", "malady", "father's_day", "comfort", "lustrum", "pedant", "dawn", "homelessness", "downtime", "mid-november", "unsusceptibility", "st_patrick's_day", "sling", "services", "hospitalization", "mummification", "lag", "brutalization", "silver_age", "susceptibility", "skipper", "cy_pres", "dryness", "initiate", "philomath", "high_ground", "running_time", "ordination", "lactosuria", "bear", "participation", "diversity", "reinstatement", "menorrhagia", "century", "condemnation", "play", "behave", "bring", "danger", "ascend", "orbit_period", "leakiness", "texas_independence_day", "hairlessness", "safety", "fortnight", "call-back", "workload", "impropriety", "withdrawer", "hour", "orderliness", "urbanization", "identification", "quinquennium", "telecommuting", "oblige", "impaction", "major", "bout", "licentiate", "wedding_day", "incubation_period", "mother's_day", "oligomenorrhea", "place", "dog_days", "three-mile_limit", "arabist", "toehold", "light", "nationality", "restriction", "mode", "porter", "field_day", "arbor_day", "ell", "nonreader", "upper_limit", "coextension", "hyperextension", "quadrennium", "shelf_life", "golden_age", "astigmatism", "enfranchise", "high_profile", "fullness", "decline", "rubber_stamp", "rustiness", "work_time", "carry", "admission_day", "new_year's_eve", "sanitary_condition", "regularization", "standardization", "judgment_day", "automation", "schoolman", "stoop", "face", "american_indian_day", "bring_in", "great_year", "unsoundness", "scandalization", "trimester", "bronze_age", "honeymoon", "uptime", "youth", "loan_approval", "long_time", "vedist", "engagement", "conform_to", "guidepost", "calendar_month", "musicologist", "valedictorian", "application", "economic_condition", "quarter", "muscle", "high_status", "mid-october", "clotting_time", "republish", "wash_up", "low_status", "facilitation", "ennoblement", "eye_condition", "climate", "frizz", "hyalinization", "disorderliness", "health", "flower", "reign", "tension", "dishabille", "environmental_condition", "week", "innocence", "jefferson_davis'_birthday", "lordship", "mid-september", "footing", "encapsulation", "patriot's_day", "irradiation", "doctor", "piggyback", "midwinter", "devaluation", "deification", "goliard", "salutatorian", "niche", "ski_conditions", "olympiad", "time_limit", "midafternoon", "robert_e_lee's_birthday", "haunt", "wykehamist", "nomination", "reader", "leadership", "underachiever", "occupation", "puerperium", "practice", "off-day", "deal", "forgive", "usance", "mujtihad", "charge", "misuse", "watch", "era", "pension", "lug", "mid-may", "difficulty", "prohibition", "keep_tabs_on", "valentine_day", "range", "tide", "date", "absolution", "historian", "city_limit", "holy_order", "master", "phase", "theologian", "workday", "tailgate", "midweek", "run", "financial_condition", "shape-up", "scholiast", "retain", "washington's_birthday", "vet", "cutoff", "pack", "public_service", "postdoc", "mid-december", "serration", "confirm", "atmosphere", "minion", "paper_route", "drought", "air_alert", "rubberstamp", "bimillennium", "mid-july", "toe_the_line", "minimum", "washday", "ivy_leaguer", "imperium", "edge", "physical_condition", "passer", "year", "anniversary", "phase_of_the_moon", "booking", "virginity", "power_of_appointment", "may_day", "red-letter_day", "sixth-former", "quantify", "fluster", "lease", "mid-january", "shoulder", "gazette", "port", "mid-august", "rag_day", "law_student", "time_of_life", "time", "limitation", "atonicity", "life", "situation", "certification", "citizenship_day", "protuberance", "lincoln's_birthday", "islamist", "walpurgis_night", "millennium", "auditor", "sinologist", "silly_season", "bimester", "calendar_day", "flag_day", "gun_control", "equality", "season", "overachiever", "indiction", "v-day", "united_nations_day", "humanist", "mid-june", "multistage", "shakespearian", "retransmit", "halloween", "invigilate", "rustication", "coaching", "exploitation", "ice_age", "commencement_day", "evening", "cabalist", "time_off", "novitiate", "age_limit", "tet", "april_fools'", "diversification", "delegating", "masorete", "times", "speech_day", "emptiness", "vacuolization", "timing", "lower_limit", "pedestal", "adhere", "fly", "chariot", "noise_conditions", "night", "carte_blanche", "guilt", "mid-february", "armed_forces_day", "nakedness", "crammer", "stigmatism", "question_time", "indian_summer", "trial_period", "poise", "weekend", "payday", "etonian", "commission", "soundness", "knife-edge", "normality", "bucket", "haul", "afternoon", "polarization", "legal_status", "guard", "bibliophile", "fruition", "degree_of_freedom", "cox", "service", "festival", "immunity", "prognathism", "extremum", "today", "window", "art_student", "ides", "thermal_barrier", "decade", "mid-april", "generation", "bibliographer", "bastardy", "impurity", "left-handedness", "back", "subservience", "mechanization", "seafaring", "election", "visa", "sanction", "renaissance_man", "holiday", "celibacy", "submission", "need", "circumstance", "starkness", "elapsed_time", "morning", "laxness", "give", "purity", "mid-march", "suspension_point", "return", "travel_time", "motivation", "hopefulness", "yesterday", "repair", "time_frame", "go_by", "pipe_in", "academician", "enlistment", "iron_age", "command"], "meronyms_list": ["new_river", "west", "louisiana", "patriot's_day", "new_hampshire", "judicial_branch", "north_carolina", "epoch", "missouri", "connecticut", "executive_branch", "south_carolina", "ohio", "north_dakota", "hour", "sunbelt", "day", "louisiana_purchase", "yosemite", "iowa", "pacific_northwest", "oregon", "noon", "mid-atlantic_states", "alaska", "colony", "plankton", "april_fools'", "idaho", "new_york", "hawaii", "indiana", "midwest", "nevada", "maryland", "pan_american_day", "maine", "tennessee", "night", "arizona", "mississippi", "kansas", "arkansas", "wyoming", "georgia", "florida", "dakota", "west_virginia", "illinois", "east", "virginia", "rio_grande", "yukon", "wisconsin", "new_jersey", "north", "rhode_island", "oklahoma", "colorado", "american", "pennsylvania", "massachusetts", "alabama", "saint_lawrence", "mid-april", "extension_course", "american_state", "south", "twin", "legislative_branch", "utah", "nekton", "great_lakes", "montana", "district_of_columbia", "vermont", "michigan", "new_england", "kentucky", "morning", "delaware", "washington", "new_mexico", "niobrara", "minnesota", "texas", "nebraska", "niagara", "california", "south_dakota"], "holonyms_list": ["teacher-student_relation", "playing_period", "gregorian_calendar", "day", "era", "organization_of_american_states", "filename", "north_america", "north_atlantic_treaty_organization", "building"], "synonyms_list": ["limitation", "comport", "work", "empowerment", "stick_to", "release", "twenty-four_hour_period", "pupil", "say-so", "extension_phone", "time_period", "total", "authority", "filename_extension", "Modern", "rule", "prolongation", "behave", "period", "USA", "keep_an_eye_on", "come", "survey", "US", "full_stop", "comply", "keep_up", "university_extension", "deport", "novel", "bear", "stop", "dependent", "dependant", "regulating", "succeed", "transmit", "extension", "America", "sidereal_day", "period_of_time", "newfangled", "full_point", "terminus_ad_quem", "day", "boundary", "U.S._government", "accord", "hold", "elongation", "come_after", "allot", "use", "propagation", "aggregate", "sum", "stock", "print", "regulation", "abide_by", "have_a_bun_in_the_oven", "concede", "limit_point", "educatee", "accompany", "watch", "conglomeration", "dominance", "cede", "status", "menstruum", "O.K.", "observe", "watch_over", "pursue", "grant", "annex", "parameter", "express", "issue", "U.S.", "United_States_of_America", "okay", "terminal_point", "trace", "point_of_accumulation", "take_after", "postdate", "deed_over", "stick_with", "Apr", "days", "channel", "run", "employ", "young", "annexe", "adopt", "approve", "contain", "sway", "United_States_government", "Day", "put_out", "play_along", "convey", "employment", "Clarence_Shepard_Day_Jr.", "extension_service", "usage", "totality", "unemployed", "authorization", "pack", "follow", "gestate", "scholar", "flow", "bookman", "write", "allow", "fall_out", "be", "US_Government", "point", "reference", "raw", "student", "fresh", "carry", "congeries", "yield", "utilisation", "regularization", "wing", "menstruation", "daytime", "parametric_quantity", "stockpile", "new", "the_States", "travel_along", "geological_period", "twenty-four_hours", "surveil", "post", "transport", "persuade", "solar_day", "acquit", "demarcation", "impart", "catamenia", "sanction", "unemployment", "position", "lengthiness", "keep_abreast", "potency", "menses", "24-hour_interval", "argument", "demarcation_line", "engagement", "conform_to", "mean_solar_day", "authorisation", "file_name_extension", "bound", "scholarly_person", "Clarence_Day", "extend", "publish", "limit", "U.S.A.", "United_States", "daylight", "give", "New", "unexampled", "expect", "award", "condition", "mandate", "dribble", "April", "conduct", "utilization", "exercise", "ordinance", "regularisation", "denotation", "years", "bring_out", "espouse", "initial", "telephone_extension", "take"]}