{"question": "90 days have passed since the Notice of Action receipt date. What can I do?", "answer": "\nVerify your status at the\u00a0USCIS Case Status Online(link is external). If your EAD application has been approved you will need to wait until the card arrives (2-4 weeks after it is approved). If the application is still pending, see an advisor at Berkeley International Office.\n", "sentence_tokenizer": ["90 days have passed since the Notice of Action receipt date.", "What can I do?", "Verify your status at the\u00a0USCIS Case Status Online(link is external).", "If your EAD application has been approved you will need to wait until the card arrives (2-4 weeks after it is approved).", "If the application is still pending, see an advisor at Berkeley International Office."], "words_tokenizer": ["90", "days", "have", "passed", "since", "the", "Notice", "of", "Action", "receipt", "date", ".", "What", "can", "I", "do", "?", "Verify", "your", "status", "at", "the", "USCIS", "Case", "Status", "Online", "(", "link", "is", "external", ")", ".", "If", "your", "EAD", "application", "has", "been", "approved", "you", "will", "need", "to", "wait", "until", "the", "card", "arrives", "(", "2-4", "weeks", "after", "it", "is", "approved", ")", ".", "If", "the", "application", "is", "still", "pending", ",", "see", "an", "advisor", "at", "Berkeley", "International", "Office", "."], "words_without_stop_words": ["90", "days", "passed", "since", "Notice", "Action", "receipt", "date", ".", "What", "I", "?", "Verify", "status", "USCIS", "Case", "Status", "Online", "(", "link", "external", ")", ".", "If", "EAD", "application", "approved", "need", "wait", "card", "arrives", "(", "2-4", "weeks", "approved", ")", ".", "If", "application", "still", "pending", ",", "see", "advisor", "Berkeley", "International", "Office", "."], "words_with_stemming": ["90", "day", "pass", "sinc", "notic", "action", "receipt", "date", ".", "what", "i", "?", "verifi", "status", "usci", "case", "status", "onlin", "(", "link", "extern", ")", ".", "if", "ead", "applic", "approv", "need", "wait", "card", "arriv", "(", "2-4", "week", "approv", ")", ".", "if", "applic", "still", "pend", ",", "see", "advisor", "berkeley", "intern", "offic", "."], "words_with_lemmatization": ["90", "day", "pass", "since", "Notice", "Action", "receipt", "date", ".", "What", "I", "?", "Verify", "status", "USCIS", "Case", "Status", "Online", "(", "link", "external", ")", ".", "If", "EAD", "application", "approve", "need", "wait", "card", "arrives", "(", "2-4", "week", "approve", ")", ".", "If", "application", "still", "pending", ",", "see", "advisor", "Berkeley", "International", "Office", "."], "words_with_pos_tags": [["90", "CD"], ["days", "NNS"], ["passed", "VBN"], ["since", "IN"], ["Notice", "NNP"], ["Action", "NNP"], ["receipt", "NN"], ["date", "NN"], [".", "."], ["What", "WP"], ["I", "PRP"], ["?", "."], ["Verify", "NNP"], ["status", "NN"], ["USCIS", "NNP"], ["Case", "NNP"], ["Status", "NNP"], ["Online", "NNP"], ["(", "("], ["link", "VBP"], ["external", "NN"], [")", ")"], [".", "."], ["If", "IN"], ["EAD", "JJ"], ["application", "NN"], ["approved", "VBD"], ["need", "JJ"], ["wait", "FW"], ["card", "NN"], ["arrives", "NNS"], ["(", "("], ["2-4", "JJ"], ["weeks", "NNS"], ["approved", "VBD"], [")", ")"], [".", "."], ["If", "IN"], ["application", "NN"], ["still", "RB"], ["pending", "JJ"], [",", ","], ["see", "VB"], ["advisor", "JJ"], ["Berkeley", "NNP"], ["International", "NNP"], ["Office", "NNP"], [".", "."]], "parse_tree_string": "(ROOT\n  (S\n    (NP (CD 90) (NNS days))\n    (VP (VBP have)\n      (VP (VBN passed)\n        (PP (IN since)\n          (NP\n            (NP (DT the) (NNP Notice))\n            (PP (IN of)\n              (NP (NNP Action) (NN receipt) (NN date)))))))\n    (. .)))(ROOT\n  (SBARQ\n    (WHNP (WDT What))\n    (SQ (MD can)\n      (NP (PRP I))\n      (VP (VB do)))\n    (. ?)))(ROOT\n  (S\n    (VP (VB Verify)\n      (NP (PRP$ your) (NN status))\n      (PP (IN at)\n        (NP\n          (NP (DT the) (NNP USCIS) (NNP Case) (NNP Status) (NNP Online))\n          (PRN (-LRB- -LRB-)\n            (S\n              (NP (NN link))\n              (VP (VBZ is)\n                (ADJP (JJ external))))\n            (-RRB- -RRB-)))))\n    (. .)))(ROOT\n  (S\n    (SBAR (IN If)\n      (S\n        (NP (PRP$ your) (NN EAD) (NN application))\n        (VP (VBZ has)\n          (VP (VBN been)\n            (VP (VBN approved))))))\n    (NP (PRP you))\n    (VP (MD will)\n      (VP (VB need)\n        (S\n          (VP (TO to)\n            (VP (VB wait)\n              (SBAR (IN until)\n                (S\n                  (NP (DT the) (NN card))\n                  (VP\n                    (VP (VBZ arrives))\n                    (PRN (-LRB- -LRB-)\n                      (SBAR\n                        (NP (CD 2-4) (NNS weeks))\n                        (IN after)\n                        (S\n                          (NP (PRP it))\n                          (VP (VBZ is)\n                            (VP (VBN approved)))))\n                      (-RRB- -RRB-))))))))))\n    (. .)))(ROOT\n  (S\n    (SBAR (IN If)\n      (S\n        (NP (DT the) (NN application))\n        (VP (VBZ is)\n          (ADVP (RB still))\n          (ADJP (VBG pending)))))\n    (, ,)\n    (VP (VB see)\n      (NP (DT an) (NN advisor))\n      (PP (IN at)\n        (NP (NNP Berkeley) (NNP International) (NNP Office))))\n    (. .)))", "hypernyms_list": ["exhaust", "request", "bed_linen", "manual_labor", "work", "staff", "life", "ordain", "throw", "type", "rite", "greeting", "mechanism", "time_period", "authority", "record", "calendar_day", "action", "excel", "roll", "cardboard", "change_hands", "care", "receive", "present", "opportunity", "linkage", "change", "acquiring", "succeed", "attention", "day", "receptacle", "advance", "occupation", "verify", "travel", "communication_system", "containerful", "see", "declare", "positive_identification", "use", "adult", "let", "framework", "transfer", "remedy", "test", "problem", "watch", "era", "accompany", "understand", "shape", "printed_circuit", "circuit", "effort", "plot", "consort", "imagine", "tour", "act", "state_of_mind", "meeting", "paper", "channel", "person", "fact", "evaluate", "experience", "move", "convey", "consider", "union", "fastener", "state", "sign", "proceeding", "be", "point", "confirm", "work_time", "humorist", "process", "authorize", "detect", "drive", "edible_fruit", "visit", "happening", "psychological_feature", "acknowledgment", "covering", "telling", "sidereal_time", "think", "administrative_unit", "linear_unit", "container", "bet", "instruction", "socialism", "permit", "time_unit", "correspondence", "program", "poverty", "companion", "undergo", "perceive", "housing", "argument", "group_action", "calendar_month", "bill", "disappear", "circumstance", "change_state", "grammatical_category", "duty", "review", "condition", "place_of_business", "necessity", "announcement", "calendar_year", "inactivity", "pause", "time"], "hyponyms_list": ["irrational_motive", "cut", "saturation", "moratorium", "security_consultant", "caste", "flash_card", "release", "gunlock", "trophy_case", "transduction", "enjoy", "paving", "immigration_and_naturalization_service", "nobility", "retirement", "psychic_energy", "accountantship", "receivership", "wise_up", "demagnetization", "despair", "foremanship", "presidency", "chemical_process", "unicameral_script", "squeak_by", "trip_up", "filtration", "stub", "materialization", "winter", "greeting_card", "food_and_drug_administration", "eve", "exude", "claim", "blockade", "liniment", "briefcase", "preservation", "desorption", "iniquity", "discomfort", "united_states_army", "see", "financial_management_service", "saltation", "investment_adviser", "run_by", "soldier", "civil_action", "accomplishment", "check", "sojourn", "military_adviser", "school_day", "united_states_air_force", "slot", "divine_office", "serve", "polling_day", "way", "test", "wetness", "sleeve", "saint's_day", "dominance", "social_station", "standing", "rain_date", "groundhog_day", "politeness", "pan_american_day", "aeration", "legation", "lieutenancy", "crash", "media_consultant", "lunar_day", "go_off", "improvement", "commandership", "law_enforcement_agency", "stool", "baggage", "magnetization", "call", "hardening", "tomorrow", "anointing", "gearbox", "prepossession", "shiva", "supervene", "slum", "thing", "synchronize", "calamine_lotion", "minister", "abort", "overdrive", "appreciate", "caliphate", "approve", "tiling", "vomit", "leap_day", "market_day", "cycle", "fumigation", "get_the_goods", "sinecure", "license", "keycard", "cinco_de_mayo", "november_5", "consider", "future_date", "bicameral_script", "tinning", "midsummer_eve", "bureau_of_engraving_and_printing", "mutism", "negotiate", "phase_change", "convection", "baronetage", "ionization", "capitalize", "breeze_through", "credit_application", "attorneyship", "spiritualize", "reference", "prosecution", "kit", "councillorship", "cinch", "rank", "lubrication", "mythicize", "inauguration_day", "come_around", "trusteeship", "entrust", "morrow", "pastorship", "make", "dignity", "anchorage", "curvature", "letter_case", "develop", "relativize", "criminal_suit", "silence", "lining", "stewardship", "eye-lotion", "summer", "exoneration", "tilth", "nominative", "screen_font", "bureau_of_customs", "united_states_public_health_service", "war_power", "capture", "reconsider", "psychological_state", "malady", "national_institute_of_standards_and_technology", "father's_day", "comfort", "operate", "rabbinate", "amicus_curiae", "distillation", "national_climatic_data_center", "second_fiddle", "proconsulship", "homelessness", "allegorize", "succumb", "unsusceptibility", "st_patrick's_day", "traverse", "cover", "transfusion", "countinghouse", "hospitalization", "united_states_fish_and_wildlife_service", "rubbing_alcohol", "chromatography", "neurolemma", "mummification", "fly_by", "cadetship", "naval_underwater_warfare_center", "message", "fashion_consultant", "premiership", "brutalization", "succession", "susceptibility", "chaplaincy", "national_guard_bureau", "necessity", "dryness", "acknowledge", "air_force_intelligence_surveillance_and_reconnaissance", "cardcase", "bruxism", "pawn_ticket", "transpiration", "high_ground", "civil_suit", "primateship", "geological_process", "ordination", "lactosuria", "size_up", "writing_desk", "punched_card", "take", "foreign_service", "internal_revenue_service", "curatorship", "participation", "diversity", "protectorship", "resistance", "reinstatement", "antitrust_case", "condemnation", "bureau_of_the_census", "befall", "play", "caveat", "concretion", "emphasizing", "boldface", "browser", "loan_application", "police_action", "danger", "while_away", "word_processor", "directorship", "survey", "beggary", "viziership", "opacification", "texas_independence_day", "hairlessness", "leakiness", "safety", "skirt", "receive", "government_accounting_office", "khanate", "defense", "blind_date", "impropriety", "auscultate", "office_of_naval_intelligence", "relay", "portfolio", "interaction", "womanhood", "extension", "busyness", "decay", "tryst", "orderliness", "urbanization", "identification", "bridge", "prelacy", "movement", "effervescence", "impaction", "transportation_security_administration", "sell-by_date", "hold", "adiabatic_process", "loan_office", "wedding_day", "like", "result", "acidification", "break", "mother's_day", "technology_administration", "behavior", "place", "know", "dispatch_case", "include", "deanship", "birthday", "applet", "wardership", "toehold", "light", "respect", "nationality", "turn_out", "mode", "thread", "internship", "field_day", "little_office", "discover", "antiredeposition", "viceroyship", "arbor_day", "leach", "department_of_defense_laboratory_system", "pair_production", "precentorship", "amphibious_landing", "thaneship", "proportional_font", "hot_seat", "beauty_consultant", "county_agent", "show_bill", "war", "overlordship", "condensation", "employment", "ethical_motive", "marshalship", "extinction", "astigmatism", "approbate", "residency", "high_profile", "fullness", "decline", "concatenation", "dismissal", "centrifugation", "rustiness", "interconnection", "advanced_research_and_development_activity", "proofread", "sainthood", "carry", "admission_day", "new_year's_eve", "pump_action", "sanitary_condition", "regularization", "admiralty", "standardization", "judgment_day", "literalize", "naval_air_warfare_center_weapons_division", "starve", "vitrification", "preview", "hat", "intersect", "automation", "shoe", "mayoralty", "test_case", "cross-check", "speakership", "vacation", "face", "american_indian_day", "headship", "alienation", "instructorship", "membership_card", "unsoundness", "protest", "scandalization", "national_geospatial-intelligence_agency", "management_consultant", "center_for_disease_control_and_prevention", "remark", "associateship", "box_office", "rag", "economy", "consulship", "send_a_message", "read_between_the_lines", "managership", "business_card", "job", "peruse", "transit", "kindness", "misconstrue", "united_states_navy", "application", "reify", "bureau_of_justice_statistics", "economic_condition", "ration_card", "captainship", "regency", "muscle", "destabilization", "high_status", "low_status", "facilitation", "apprenticeship", "flocculation", "recur", "backroom_boy", "ennoblement", "eye_condition", "climate", "frizz", "hyalinization", "client", "disorderliness", "health", "tension", "curdling", "chance", "dishabille", "environmental_condition", "principalship", "ascertain", "electronic_warfare", "jefferson_davis'_birthday", "innocence", "blackwash", "lack", "preceptorship", "footing", "quiver", "encapsulation", "patriot's_day", "irradiation", "class_action", "boot", "pc_board", "vice-presidency", "incumbency", "chairmanship", "frame", "tipster", "soak", "slip", "epoch", "oscillation", "deification", "pillbox", "jacket", "proctorship", "sweat", "niche", "spot-check", "ski_conditions", "donor_card", "office_of_intelligence_support", "editor_program", "wardenship", "piano_action", "midafternoon", "drift", "department_of_energy_intelligence", "typewriter_font", "robert_e_lee's_birthday", "referral", "starets", "evacuate", "sorption", "nomination", "inspect", "magistracy", "leadership", "articulation", "sympathy_card", "moot", "newsroom", "urge", "off-day", "break_through", "galvanization", "tribuneship", "deal", "mind", "custodianship", "naval_surface_warfare_center", "generalship", "peasanthood", "stimulation", "defense_technical_information_center", "curacy", "moderatorship", "suffer", "glasses_case", "national_oceanic_and_atmospheric_administration", "playing_card", "difficulty", "prohibition", "spraying", "valentine_day", "date", "performance", "plastering", "coherence", "fatherhood", "absolution", "patent_and_trademark_office_database", "happen", "apostleship", "transgression", "identify", "holy_order", "patent_application", "oxygenation", "walkie-talkie", "res_gestae", "workday", "clear", "formation", "run", "fetch", "eruption", "financial_condition", "controllership", "eldership", "messiahship", "candle", "search", "pass_off", "wallet", "anticipate", "contact", "humiliation", "piece", "waxing", "federal_aviation_agency", "washington's_birthday", "node", "active_application", "hyperlink", "judgeship", "arise", "glimpse", "job_application", "chancellorship", "counterterrorist_center", "proceed", "feel", "serration", "confirm", "atmosphere", "treasurership", "executive_agency", "counselorship", "rubberstamp", "plant", "nuclear_reaction", "teachership", "washday", "hand_over", "pass_through", "marine_corps_intelligence_activity", "temperature_change", "united_states_coast_guard", "editorship", "priorship", "national_technical_information_service", "anniversary", "physical_condition", "office_of_the_dead", "rectorship", "defense_information_systems_agency", "rational_motive", "concur", "idealize", "battle", "feedback", "scattering", "predecease", "virginity", "source", "prix_fixe", "witness", "postcard", "choice", "may_day", "perceive", "army_intelligence", "papering", "font_cartridge", "deem", "prize", "red-letter_day", "attest", "locket", "catch_sight", "lock", "timecard", "behold", "legislatorship", "rub", "defense_advanced_research_projects_agency", "library_card", "united_states_government_printing_office", "expect", "fossilization", "plating", "transpire", "visualize", "natural_language_processor", "sortie", "buy_it", "survival", "rag_day", "control", "watch_case", "librarianship", "misapplication", "governorship", "intervene", "bureau_of_intelligence_and_research", "time", "rulership", "oblique", "stiffening", "cardinalship", "comptroller_of_the_currency", "request", "get_across", "atonicity", "a_la_carte", "foliation", "life", "situation", "x-ray", "certificate", "citizenship_day", "lincoln's_birthday", "protuberance", "life_office", "discipleship", "walpurgis_night", "painting", "spectate", "zip_by", "headquarters", "casualty_care_research_center", "manhood", "urinate", "organ", "flag_day", "come", "double_date", "read", "operation", "diffusion", "executive_clemency", "transgress", "stead", "praetorship", "aggression", "equality", "holy_week", "week_from_monday", "change", "sans_serif", "medullary_sheath", "menthol", "v-day", "united_nations_day", "shipping_office", "welfare_case", "playing", "technology", "halloween", "rustication", "mastership", "bailiffship", "tarot_card", "prefecture", "declare", "commencement_day", "senatorship", "evening", "autopsy", "ballistic_missile_defense_organization", "radiate", "comptrollership", "absorption", "tet", "studentship", "april_fools'", "diversification", "sericulture", "italic", "naval_special_warfare", "speech_day", "fall", "emptiness", "vacuolization", "emirate", "pedestal", "assure", "ambassadorship", "fly", "compact", "noise_conditions", "render", "lis_pendens", "guilt", "scumble", "public_office", "armed_forces_day", "favor", "secretaryship", "nakedness", "educe", "witch_hazel", "stigmatism", "fumble", "bishopry", "plum", "get_by", "weekend", "payday", "dissolution", "throne", "lectureship", "commission", "ion_exchange", "soundness", "united_states_border_patrol", "suffocate", "normality", "counterclaim", "double-check", "afternoon", "academicianship", "card", "polarization", "maturity", "flow", "legal_status", "radiation", "clerkship", "countersuit", "fruition", "swing", "gothic", "lorica", "national_park_service", "immunity", "prognathism", "course", "gun_case", "abstract", "today", "federal_housing_administration", "independent_agency", "ides", "husk", "cpu_board", "agency", "cigarette_case", "trading_card", "electrophoresis", "drown", "tend", "backfire", "bastardy", "national_weather_service", "table_d'hote", "reverence", "infiltrate", "impurity", "national_institutes_of_health", "capacity", "left-handedness", "professorship", "inspectorship", "back", "pickings", "subservience", "mechanization", "jumpstart", "occupational_safety_and_health_administration", "nonproliferation_center", "validate", "election", "vampirism", "bureau_of_justice_assistance", "visa", "precession_of_the_equinoxes", "catch", "sanction", "retardation", "seigniory", "chieftaincy", "go_far", "holiday", "get-well_card", "celibacy", "submission", "inactivation", "establishment", "need", "arrival", "bill_of_lading", "circumstance", "government_office", "solicitorship", "take_in", "obituary", "sink", "paternity_suit", "give", "saber_rattling", "laxness", "disrespect", "purity", "reinterpret", "local_authority", "extraction", "bureau_of_diplomatic_security", "softening", "theca", "scan", "motivation", "hopefulness", "synergy", "defense_logistics_agency", "yesterday", "repair", "custody_case", "counselor", "stupefaction", "patient", "defense_reutilization_and_marketing_service", "beatification", "command"], "meronyms_list": ["weekend", "cleanup", "date", "noon", "day", "morning", "calendar_day", "midweek", "night", "key", "internationalist", "university_of_california_at_berkeley", "hour", "day_of_the_week", "workweek"], "holonyms_list": ["week", "chain", "grandfather_clock", "window", "date", "gun", "day", "doorway", "type_family", "calendar_month", "keyboard", "office_building", "date_palm", "california"], "synonyms_list": ["wait", "week", "regard", "hear", "reach", "add-in", "devolve", "carte", "pick_up", "outside", "plug-in", "pass_along", "twenty-four_hour_period", "natural_action", "situation", "type", "guide", "travel_by", "make_pass", "go_along", "fade", "authorise", "suit", "delay", "instance", "reckon", "authority", "occur", "choke", "indigence", "give-up_the_ghost", "coating", "connection", "action", "want", "calendar_week", "evanesce", "advisor", "guinea_pig", "slip", "workweek", "federal_agency", "postponement", "extraneous", "International", "make_it", "eccentric", "appointment", "wag", "penury", "carte_du_jour", "sidereal_day", "causa", "slip_away", "fancy", "slip_by", "day", "project", "bureau", "die", "fount", "verify", "hold", "international", "picture", "link", "event", "inter-group_communication", "see", "affirm", "examine", "grammatical_case", "overtake", "check", "come_about", "diligence", "determine", "consultant", "overhaul", "go_past", "radio_link", "go_out", "military_action", "adviser", "Bishop_Berkeley", "vitrine", "go_through", "get_a_line", "part", "business_office", "place", "nexus", "meet", "cause", "excrete", "hebdomad", "understand", "watch", "take_place", "croak", "fall", "pauperism", "run_into", "decease", "status", "connexion", "O.K.", "lapse", "transcend", "pass", "identity_card", "character", "pauperization", "observance", "data_link", "assure", "view", "wit", "see_to_it", "date", "glide_by", "kick_the_bucket", "particular_date", "okay", "happen", "typeface", "pass_away", "external", "exceed", "lineup", "discover", "lawsuit", "ensure", "Berkeley", "showcase", "receipt", "clear", "posting", "motive", "overstep", "perish", "compositor's_case", "days", "run", "assert", "slide_by", "office", "realise", "pass_off", "conk", "observation", "contact", "approve", "Day", "menu", "experience", "office_staff", "attend", "realize", "Clarence_Shepard_Day_Jr.", "spend", "learn", "notice", "go", "consider", "card", "billet", "notification", "swear", "construe", "turn_over", "draw", "exit", "activity", "action_at_law", "lead", "fall_out", "example", "typesetter's_case", "pillow_slip", "batting_order", "liaison", "pop_off", "day_of_the_month", "authorize", "calling_card", "fleet", "casing", "cash_in_one's_chips", "daytime", "bill_of_fare", "find_out", "visit", "agency", "ascertain", "practical_application", "shell", "figure", "envision", "face", "top", "covering", "expire", "twenty-four_hours", "government_agency", "applications_programme", "post", "case", "get_wind", "take_care", "eliminate", "spot", "subject", "solar_day", "natural_process", "sheath", "run_across", "look", "surpass", "legislate", "application_program", "function", "time_lag", "visiting_card", "board", "egest", "snuff_it", "catch", "position", "sanction", "poster", "find", "communicate", "power", "witness", "24-hour_interval", "pass_on", "insure", "reception", "encounter", "role", "scorecard", "mean_solar_day", "engagement", "pillowcase", "avow", "pass_by", "bill", "Clarence_Day", "escort", "aver", "application", "elapse", "go_on", "extend", "blow_over", "legal_action", "need", "demand", "activeness", "take_in", "daylight", "sink", "action_mechanism", "give", "drop_dead", "tie", "hand", "get_word", "circuit_card", "image", "come_across", "return", "condition", "swan", "connectedness", "circuit_board", "visualize", "interpret", "berth", "motivation", "display_case", "George_Berkeley", "put_across", "buy_the_farm", "tie-in", "go_by", "control", "years", "lotion", "linkup", "waiting", "visualise", "go_steady", "placard", "font", "caseful", "go_across", "hap"]}