{"question": "My EAD says \"not valid for re-entry\" on it. Does that mean I cannot travel abroad and re-enter on OPT?", "answer": "\nIt simply means that you must carry other documents to show proof of your eligibility to re-enter the U.S. such as your I-20 and valid F-1 visa stamp. The EAD alone is not enough to re-enter the U.S.\n", "sentence_tokenizer": ["My EAD says \"not valid for re-entry\" on it.", "Does that mean I cannot travel abroad and re-enter on OPT?", "It simply means that you must carry other documents to show proof of your eligibility to re-enter the U.S. such as your I-20 and valid F-1 visa stamp.", "The EAD alone is not enough to re-enter the U.S."], "words_tokenizer": ["My", "EAD", "says", "``", "not", "valid", "for", "re-entry", "''", "on", "it", ".", "Does", "that", "mean", "I", "can", "not", "travel", "abroad", "and", "re-enter", "on", "OPT", "?", "It", "simply", "means", "that", "you", "must", "carry", "other", "documents", "to", "show", "proof", "of", "your", "eligibility", "to", "re-enter", "the", "U.S.", "such", "as", "your", "I-20", "and", "valid", "F-1", "visa", "stamp", ".", "The", "EAD", "alone", "is", "not", "enough", "to", "re-enter", "the", "U.S", "."], "words_without_stop_words": ["My", "EAD", "says", "``", "valid", "re-entry", "''", ".", "Does", "mean", "I", "travel", "abroad", "re-enter", "OPT", "?", "It", "simply", "means", "must", "carry", "documents", "show", "proof", "eligibility", "re-enter", "U.S.", "I-20", "valid", "F-1", "visa", "stamp", ".", "The", "EAD", "alone", "enough", "re-enter", "U.S", "."], "words_with_stemming": ["my", "ead", "say", "``", "valid", "re-entri", "''", ".", "doe", "mean", "i", "travel", "abroad", "re-ent", "opt", "?", "it", "simpli", "mean", "must", "carri", "document", "show", "proof", "elig", "re-ent", "u.s.", "i-20", "valid", "f-1", "visa", "stamp", ".", "the", "ead", "alon", "enough", "re-ent", "u.", "."], "words_with_lemmatization": ["My", "EAD", "say", "``", "valid", "re-entry", "''", ".", "Does", "mean", "I", "travel", "abroad", "re-enter", "OPT", "?", "It", "simply", "mean", "must", "carry", "document", "show", "proof", "eligibility", "re-enter", "U.S.", "I-20", "valid", "F-1", "visa", "stamp", ".", "The", "EAD", "alone", "enough", "re-enter", "U.S", "."], "words_with_pos_tags": [["My", "PRP$"], ["EAD", "NNP"], ["says", "VBZ"], ["``", "``"], ["valid", "JJ"], ["re-entry", "NN"], ["''", "''"], [".", "."], ["Does", "NNP"], ["mean", "VB"], ["I", "PRP"], ["travel", "VBP"], ["abroad", "RB"], ["re-enter", "JJ"], ["OPT", "NNP"], ["?", "."], ["It", "PRP"], ["simply", "RB"], ["means", "VBZ"], ["must", "MD"], ["carry", "VB"], ["documents", "NNS"], ["show", "VBP"], ["proof", "JJ"], ["eligibility", "NN"], ["re-enter", "JJ"], ["U.S.", "NNP"], ["I-20", "NNP"], ["valid", "JJ"], ["F-1", "NNP"], ["visa", "NN"], ["stamp", "NN"], [".", "."], ["The", "DT"], ["EAD", "NNP"], ["alone", "RB"], ["enough", "RB"], ["re-enter", "JJ"], ["U.S", "NNP"], [".", "."]], "parse_tree_string": "(ROOT\n  (S\n    (NP (PRP$ My) (NN EAD))\n    (VP (VBZ says)\n      (ADJP (`` ``)\n        (ADJP (RB not) (JJ valid)\n          (PP (IN for)\n            (NP (NN re-entry))))\n        ('' '')\n        (PP (IN on)\n          (NP (PRP it)))))\n    (. .)))(ROOT\n  (S\n    (VP (VBZ Does)\n      (SBAR (IN that)\n        (S\n          (NP\n            (NP (NN mean))\n            (NP (PRP I)))\n          (VP (MD can) (RB not)\n            (VP\n              (VP (VB travel)\n                (ADVP (RB abroad)))\n              (CC and)\n              (VP (VB re-enter)\n                (PP (IN on)\n                  (NP (NNP OPT)))))))))\n    (. ?)))(ROOT\n  (S\n    (NP (PRP It))\n    (ADVP (RB simply))\n    (VP (VBZ means)\n      (SBAR (IN that)\n        (S\n          (NP (PRP you))\n          (VP (MD must)\n            (VP (VB carry)\n              (NP (JJ other) (NNS documents))\n              (S\n                (VP (TO to)\n                  (VP (VB show)\n                    (NP\n                      (NP (NN proof))\n                      (PP (IN of)\n                        (NP (PRP$ your) (NN eligibility)\n                          (S\n                            (VP (TO to)\n                              (VP (VB re-enter)\n                                (NP\n                                  (NP (DT the) (NNP U.S.))\n                                  (PP (JJ such) (IN as)\n                                    (NP\n                                      (NP (PRP$ your) (NN I-20))\n                                      (CC and)\n                                      (NP (JJ valid) (NN F-1) (NN visa) (NN stamp)))))))))))))))))))\n    (. .)))(ROOT\n  (S\n    (NP\n      (NP (DT The) (NN EAD))\n      (ADVP (RB alone)))\n    (VP (VBZ is) (RB not)\n      (ADJP (JJ enough)\n        (S\n          (VP (TO to)\n            (VP (VB re-enter)\n              (NP (DT the) (NNP U.S.)))))))))", "hypernyms_list": ["sheet", "request", "have", "convey", "motion", "sanction", "machine", "writing", "executive_department", "demonstration", "pretense", "average", "device", "argument", "implementation", "entertainment", "recite", "read", "impression", "instrumentality", "express", "social_event", "evidence", "class", "speculate", "token", "federal_government", "placental", "qualification", "symbol", "determination", "representation", "medium_of_exchange", "computer_file", "movement", "photographic_print", "die", "capital", "communication", "measure", "solid", "assert", "transportation"], "hyponyms_list": ["commercial_document", "riding", "flap", "galanty_show", "certificate", "creep", "escape", "variety_show", "voice", "play", "piggyback", "syllabize", "open_sesame", "debt_instrument", "record", "wings", "ice_show", "crossing", "spread", "resignation", "retroflex", "portage", "roll", "galley_proof", "foundry_proof", "present", "trill", "specification", "signet", "tooth", "answer", "click", "monetization", "direct", "sibilate", "documentation", "desperate_measure", "entrance", "ballot", "horseshow", "journey", "legal_document", "declare", "confession", "voucher", "vocalize", "wild_west_show", "stage", "step", "fireman's_carry", "letter_of_credit", "dog_show", "display", "twang", "junketing", "presentation", "gait", "peregrination", "salvation", "patent", "traversal", "fall", "stress", "insurability", "stampede", "report", "brevet", "pocketbook", "raise", "performance", "handstamp", "lisp", "dint", "stage_dancing", "aspirate", "interlude", "cachet", "call", "wherewithal", "circus", "drawl", "fast_track", "broadcast", "expedient", "misstate", "run", "staging", "get_out", "cabaret", "wayfaring", "lilt", "road_show", "note", "ascii_text_file", "announce", "charter", "harmonic_mean", "instrument", "imprint", "copyright", "seal", "mathematical_proof", "demonstration", "enclosure", "instruct", "jog", "flow", "confirmation", "circulation", "rise", "dance_step", "puppet_show", "palatalize", "probate", "stroke", "capitulation", "progress", "summarize", "bulla", "authentication", "articulate", "porterage", "water_travel", "logical_proof", "mispronounce", "round", "driving", "papyrus", "levitation", "burlesque", "great_seal", "gravitation", "brachiation", "lap", "precede", "devoice", "plead", "air_travel", "stepping_stone", "quittance", "explode", "walk", "warn", "geometric_mean", "subvocalize", "food_stamp", "marriageability", "form", "translation", "arithmetic_mean", "source", "circumnavigation", "road", "big_stick", "nasalize", "on_the_road", "platform", "attraction", "web_page", "gaudery", "establishment", "crawl", "movie", "letter", "wandering", "packing", "give", "ascension", "resolution", "add", "sideshow", "commutation", "explain", "descent", "raree-show", "carnival", "command"], "meronyms_list": ["iowa", "florida", "oregon", "pacific_northwest", "new_river", "great_lakes", "west", "louisiana", "dakota", "alaska", "mid-atlantic_states", "montana", "west_virginia", "colony", "illinois", "east", "virginia", "rio_grande", "yukon", "new_hampshire", "wisconsin", "idaho", "yosemite", "new_jersey", "judicial_branch", "new_york", "north", "hawaii", "rhode_island", "district_of_columbia", "indiana", "north_carolina", "vermont", "louisiana_purchase", "oklahoma", "michigan", "midwest", "missouri", "maryland", "nevada", "new_england", "kentucky", "maine", "colorado", "connecticut", "executive_branch", "south_carolina", "tennessee", "american", "pennsylvania", "article", "delaware", "alabama", "massachusetts", "department_of_energy_intelligence", "ohio", "north_dakota", "saint_lawrence", "washington", "new_mexico", "american_state", "south", "preamble", "niobrara", "arizona", "minnesota", "texas", "twin", "mississippi", "legislative_branch", "sunbelt", "nebraska", "kansas", "arkansas", "wyoming", "niagara", "california", "georgia", "south_dakota", "utah"], "holonyms_list": ["battery", "passport", "organization_of_american_states", "north_america", "north_atlantic_treaty_organization"], "synonyms_list": ["enjoin", "United_States_government", "traveling", "proof", "mean", "Energy", "visa", "sound_out", "suppose", "tender", "display", "pronounce", "postage", "seal", "way", "say", "mould", "Energy_Department", "substance", "locomotion", "legal_tender", "document", "state", "eligibility", "USA", "mean_value", "appearance", "read", "US_Government", "US", "tell", "impression", "aver", "enunciate", "written_document", "carry", "trial_impression", "change_of_location", "U.S.A.", "United_States", "U.S.", "articulate", "United_States_of_America", "valid", "agency", "cogent_evidence", "postage_stamp", "text_file", "papers", "Department_of_Energy", "order", "substantiation", "pestle", "the_States", "America", "validation", "doe", "cast", "test_copy", "travelling", "enounce", "DOE", "U.S._government", "mold", "travel", "means", "allege", "revenue_stamp", "show", "stamp"]}